bilberrydb/__init__.py
bilberrydb/client.py
bilberrydb/exceptions.py
bilberrydb/vector.py
bilberrydb-1.0.0.dist-info/METADATA
bilberrydb-1.0.0.dist-info/WHEEL
bilberrydb-1.0.0.dist-info/top_level.txt
bilberrydb-1.0.0.dist-info/RECORD
