Metadata-Version: 2.4
Name: bilberrydb
Version: 1.0.0
Summary: Python SDK for BilberryDB - Image Vector Search Database
Author: BilberryDB Team
Author-email: app@bilberrydb.com
Project-URL: Bug Reports, https://github.com/bilberrydb/python-sdk/issues
Project-URL: Documentation, https://docs.bilberrydb.com
Keywords: vector database,image search,similarity search,computer vision,machine learning
Classifier: Development Status :: 4 - Beta
Classifier: Intended Audience :: Developers
Classifier: License :: OSI Approved :: MIT License
Classifier: Operating System :: OS Independent
Classifier: Programming Language :: Python :: 3
Classifier: Programming Language :: Python :: 3.7
Classifier: Programming Language :: Python :: 3.8
Classifier: Programming Language :: Python :: 3.9
Classifier: Programming Language :: Python :: 3.10
Classifier: Programming Language :: Python :: 3.11
Classifier: Topic :: Database
Classifier: Topic :: Scientific/Engineering :: Artificial Intelligence
Classifier: Topic :: Software Development :: Libraries :: Python Modules
Requires-Python: >=3.7
Dynamic: author
Dynamic: author-email
Dynamic: classifier
Dynamic: keywords
Dynamic: project-url
Dynamic: requires-python
Dynamic: summary
